{
  "avatar": "https://images.chesscomfiles.com/uploads/v1/user/371633593.ab013513.200x200o.17b51e0c3cf1.jpg",
  "player_id": 371633593,
  "@id": "https://api.chess.com/pub/player/kazuko-chan",
  "url": "https://www.chess.com/member/kazuko-chan",
  "name": "Luna (Xiaowen) Cao",
  "username": "kazuko-chan",
  "followers": 441,
  "country": "https://api.chess.com/pub/country/JP",
  "last_online": 1769086523,
  "joined": 1719232331,
  "status": "basic",
  "is_streamer": false,
  "verified": false,
  "league": "Legend",
  "streaming_platforms": []
}